{
    "type":  "ENGREMIAT_CONSTRUCTOR_PHASE_003_GLOBAL_DIAGNOSTIC",
    "ok":  true,
    "decision":  "PHASE_003_GOVERNED_CONTROL_PROMPTER_EXECUTION_CLOSED_LOCAL_ONLY",
    "phase":  "ENGREMIAT_CONSTRUCTOR_PHASE_003_GOVERNED_CONTROL_PROMPTER_EXECUTION",
    "block":  "BLOCK_008_GLOBAL_DIAGNOSTIC_AND_CLOSE",
    "project_id":  "engremiat-training-game-inclusion-001",
    "readiness":  94,
    "required_reports_count":  7,
    "ok_reports_count":  7,
    "missing_reports_count":  0,
    "missing_reports":  [

                        ],
    "failed_checks_count":  0,
    "failed_checks":  [

                      ],
    "checks":  {
                   "reports_ok":  true,
                   "control_consumer_ready":  true,
                   "prompter_execution_draft_ready":  true,
                   "constructor_control_queue_ready":  true,
                   "constructor_prompter_queue_ready":  true,
                   "full_cycle_simulation_ready":  true,
                   "unlock_gate_ready":  true,
                   "real_control_write_blocked":  true,
                   "real_prompter_execution_blocked":  true,
                   "external_api_blocked":  true,
                   "worker_real_blocked":  true
               },
    "real_control_write_allowed":  false,
    "real_prompter_execution_allowed":  false,
    "external_ai_call_allowed":  false,
    "external_api_allowed":  false,
    "worker_real_allowed":  false,
    "recommended_next_phase":  "ENGREMIAT_CONSTRUCTOR_PHASE_004_SOLUTION_BUILDER_COMMERCIAL_PACKAGE",
    "next_recommended_action":  "DECIDE_COMMIT_PHASE_003_OR_START_PHASE_004",
    "updated_at":  "2026-06-05T21:02:08"
}
